sats_receiver/__init__.py
sats_receiver/__main__.py
sats_receiver/async_signal.py
sats_receiver/executor.py
sats_receiver/librtlsdr.py
sats_receiver/manager.py
sats_receiver/observer.py
sats_receiver/tle.py
sats_receiver/utils.py
sats_receiver/gr_modules/__init__.py
sats_receiver/gr_modules/decoders.py
sats_receiver/gr_modules/demodulators.py
sats_receiver/gr_modules/modules.py
sats_receiver/gr_modules/receiver.py
sats_receiver/gr_modules/epb/__init__.py
sats_receiver/gr_modules/epb/deint.py
sats_receiver/gr_modules/epb/pdu_to_cadu.py
sats_receiver/gr_modules/epb/prober.py
sats_receiver/gr_modules/epb/sstv.py
sats_receiver/systems/__init__.py
sats_receiver/systems/apt.py
sats_receiver/systems/sstv.py
sats_receiver/systems/satellites/__init__.py
sats_receiver/systems/satellites/demodulators/__init__.py
sats_receiver/systems/satellites/filereceivers/__init__.py
sats_receiver/systems/satellites/filereceivers/geoscan.py
sats_receiver/systems/satellites/telemetry/__init__.py
sats_receiver/systems/satellites/telemetry/geoscan_tlm.py
sats_receiver/systems/satellites/telemetry/usp_tlm.py
sats_receiver-0.2.0.dist-info/licenses/LICENSE
tests/__init__.py
tests/test_async_signal.py
tests/test_decoders.py
tests/test_demodulators.py
tests/test_utils.py
sats_receiver-0.2.0.dist-info/METADATA
sats_receiver-0.2.0.dist-info/WHEEL
sats_receiver-0.2.0.dist-info/top_level.txt
sats_receiver-0.2.0.dist-info/RECORD
