Metadata-Version: 2.4
Name: sats_receiver
Version: 0.2.0
Summary: Satellites data receiver based on GNU Radio
Home-page: https://github.com/baskiton/sats-receiver
Author: Alexander Baskikh
Author-email: baskiton@gmail.com
License: MIT
Project-URL: Bug Tracker, https://github.com/baskiton/sats-receiver/issues
Classifier: License :: OSI Approved :: MIT License
Classifier: Environment :: Console
Classifier: Programming Language :: Python :: 3
Classifier: Topic :: Communications :: Ham Radio
Requires-Python: >=3.7
License-File: LICENSE
Requires-Dist: ephem
Requires-Dist: numpy
Requires-Dist: Pillow
Requires-Dist: pyshp
Requires-Dist: python-dateutil
Requires-Dist: scipy
Dynamic: author
Dynamic: author-email
Dynamic: classifier
Dynamic: description
Dynamic: description-content-type
Dynamic: home-page
Dynamic: license
Dynamic: license-file
Dynamic: project-url
Dynamic: requires-dist
Dynamic: requires-python
Dynamic: summary
